dawnai/__init__.py
dawnai/analytics.py
dawnai/version.py
dawnai-0.0.18.dist-info/METADATA
dawnai-0.0.18.dist-info/WHEEL
dawnai-0.0.18.dist-info/top_level.txt
dawnai-0.0.18.dist-info/RECORD
